yw_etl_tap_sqlalchemy/.DS_Store
yw_etl_tap_sqlalchemy/Database.py
yw_etl_tap_sqlalchemy/WorkingDirectory.py
yw_etl_tap_sqlalchemy/WorkingDirectory_test.py
yw_etl_tap_sqlalchemy/__init__.py
yw_etl_tap_sqlalchemy/logging.conf
yw_etl_tap_sqlalchemy/main.py
yw_etl_tap_sqlalchemy/utils.py
yw_etl_tap_sqlalchemy/tapstream/CustomQueryTapStream.py
yw_etl_tap_sqlalchemy/tapstream/CustomQueryTapStream_test.py
yw_etl_tap_sqlalchemy/tapstream/TapStream.py
yw_etl_tap_sqlalchemy/tapstream/__init__.py
yw_etl_tap_sqlalchemy/tapstream/helpers.py
yw_etl_tap_sqlalchemy-0.1.9.dist-info/METADATA
yw_etl_tap_sqlalchemy-0.1.9.dist-info/WHEEL
yw_etl_tap_sqlalchemy-0.1.9.dist-info/entry_points.txt
yw_etl_tap_sqlalchemy-0.1.9.dist-info/top_level.txt
yw_etl_tap_sqlalchemy-0.1.9.dist-info/RECORD
