Metadata-Version: 2.1
Name: yw_etl_tap_sqlalchemy
Version: 0.1.9
Requires-Python: >=3.10
Requires-Dist: psycopg2-binary==2.9.3
Requires-Dist: pyodbc==4.0.34
Requires-Dist: singer-python==5.12.2
Requires-Dist: SQLAlchemy==2.0.13
Requires-Dist: impyla==0.18.0
Requires-Dist: oracledb==1.3.1
